cui_gt/__init__.py
cui_gt/validators.py
cui_gt-0.2.0.dist-info/METADATA
cui_gt-0.2.0.dist-info/WHEEL
cui_gt-0.2.0.dist-info/RECORD
