Metadata-Version: 2.4
Name: cui-gt
Version: 0.2.0
Summary: Validador de CUI de Guatemala
Project-URL: Homepage, https://github.com/aalonzolu/cui-gt
Author-email: Andrés Alonzo <correo@lexo.dev>
License-Expression: MIT
Keywords: cui,guatemala,nit,validation
Classifier: License :: OSI Approved :: MIT License
Classifier: Operating System :: OS Independent
Classifier: Programming Language :: Python :: 3
Requires-Python: >=3.7
